LICENSE
pyproject.toml
src/my_test_proj1_HuangXiaolong/__init__.py
src/my_test_proj1_HuangXiaolong/example.py
src/my_test_proj3_HuangXiaolong.egg-info/PKG-INFO
src/my_test_proj3_HuangXiaolong.egg-info/SOURCES.txt
src/my_test_proj3_HuangXiaolong.egg-info/dependency_links.txt
src/my_test_proj3_HuangXiaolong.egg-info/requires.txt
src/my_test_proj3_HuangXiaolong.egg-info/top_level.txt