Metadata-Version: 2.1
Name: my_test_proj3_HuangXiaolong
Version: 0.0.1
Summary: example test project 3
Author-email: Xiaolong Huang <hxl65536@gmail.com>
Requires-Python: >=3.8
License-File: LICENSE
Requires-Dist: tqdm==4.66.3
